telebaka_toxic/__init__.py
telebaka_toxic/admin.py
telebaka_toxic/bot.py
telebaka_toxic/models.py
telebaka_toxic/preferences.py
telebaka_toxic/tasks.py
telebaka_toxic/migrations/0001_initial.py
telebaka_toxic/migrations/0002_auto_20180628_1343.py
telebaka_toxic/migrations/0003_toxicityrating_bot.py
telebaka_toxic/migrations/0004_auto_20180629_1752.py
telebaka_toxic/migrations/0005_auto_20180701_1444.py
telebaka_toxic/migrations/__init__.py
telebaka_toxic-0.1.36.dist-info/METADATA
telebaka_toxic-0.1.36.dist-info/WHEEL
telebaka_toxic-0.1.36.dist-info/top_level.txt
telebaka_toxic-0.1.36.dist-info/RECORD
