Metadata-Version: 2.1
Name: telebaka-toxic
Version: 0.1.36
Summary: UNKNOWN
Home-page: UNKNOWN
Author: bakatrouble
Author-email: bakatrouble@gmail.com
License: UNKNOWN
Platform: UNKNOWN
Requires-Dist: django
Requires-Dist: python-telegram-bot
Requires-Dist: telebakacore
